metagenomix/__init__.py
metagenomix/_hpc.py
metagenomix/_inputs.py
metagenomix/_io_utils.py
metagenomix/_metadata.py
metagenomix/creator.py
metagenomix/exporter.py
metagenomix/manager.py
metagenomix/merger.py
metagenomix/metagenomix.py
metagenomix/monitoring.py
metagenomix/core/__init__.py
metagenomix/core/commands.py
metagenomix/core/config.py
metagenomix/core/databases.py
metagenomix/core/graph.py
metagenomix/core/jobs.py
metagenomix/core/output.py
metagenomix/core/parameters.py
metagenomix/core/pipeline.py
metagenomix/core/slurm.py
metagenomix/core/software.py
metagenomix/resources/run_params.yml
metagenomix/resources/softwares.txt
metagenomix/resources/scripts/fasta4shogun.py
metagenomix/resources/scripts/sam4shogun.py
metagenomix/resources/scripts/symmetrize_simka_matrix.py
metagenomix/resources/wol/batch_down.sh
metagenomix/resources/wol/genome_sizes.txt
metagenomix/resources/wol/lineages.txt
metagenomix/resources/wol/make_down_list.py
metagenomix/resources/wol/metadata.tsv
metagenomix/resources/wol/tree.nwk
metagenomix/scripts/__init__.py
metagenomix/scripts/_standalone_metagenomix.py
metagenomix/scripts/modules/__init__.py
metagenomix/scripts/modules/create.py
metagenomix/scripts/modules/export.py
metagenomix/scripts/modules/manage.py
metagenomix/scripts/modules/merge.py
metagenomix/scripts/modules/monitor.py
metagenomix/softwares/__init__.py
metagenomix/softwares/alignment.py
metagenomix/softwares/annotation.py
metagenomix/softwares/anvio.py
metagenomix/softwares/args.py
metagenomix/softwares/assembly.py
metagenomix/softwares/binning.py
metagenomix/softwares/genomics.py
metagenomix/softwares/mapping.py
metagenomix/softwares/metamarker.py
metagenomix/softwares/midas2.py
metagenomix/softwares/phlans.py
metagenomix/softwares/plasmids.py
metagenomix/softwares/pooling.py
metagenomix/softwares/preprocess.py
metagenomix/softwares/profiling.py
metagenomix/softwares/simka.py
metagenomix/softwares/squeezemeta.py
metagenomix/softwares/strains.py
metagenomix-3.2.dist-info/LICENSE
metagenomix-3.2.dist-info/METADATA
metagenomix-3.2.dist-info/WHEEL
metagenomix-3.2.dist-info/entry_points.txt
metagenomix-3.2.dist-info/top_level.txt
metagenomix-3.2.dist-info/RECORD
