Metadata-Version: 2.1
Name: metagenomix
Version: 3.2
Summary: metagenomix is a pipeline of pipelines to conduct metagenomic analyses on Slurm/Torque
Home-page: https://github.com/FranckLejzerowicz/metagenomix
Author: Franck Lejzerowicz
Author-email: franck.lejzerowicz@gmail.com
Maintainer: Franck Lejzerowicz
Maintainer-email: franck.lejzerowicz@gmail.com
License: BSD
Classifier: License :: OSI Approved :: BSD License
Classifier: Topic :: Scientific/Engineering
Classifier: Topic :: Scientific/Engineering :: Bio-Informatics
Classifier: Programming Language :: Python :: 3.6
Classifier: Programming Language :: Python :: 3 :: Only
Classifier: Operating System :: Unix
Classifier: Operating System :: POSIX
Classifier: Operating System :: MacOS :: MacOS X
Requires-Python: >=3.6
License-File: LICENSE
Requires-Dist: click
Requires-Dist: biom-format
Requires-Dist: scikit-bio
Requires-Dist: scipy
Requires-Dist: numpy
Requires-Dist: pandas
Requires-Dist: tabulate
Requires-Dist: pyyaml
Requires-Dist: seaborn
